djangoldp_i18n/__init__.py
djangoldp_i18n/admin.py
djangoldp_i18n/apps.py
djangoldp_i18n/djangoldp_settings.py
djangoldp_i18n/serializers.py
djangoldp_i18n/views.py
djangoldp_i18n/tests/__init__.py
djangoldp_i18n/tests/apps.py
djangoldp_i18n/tests/djangoldp_urls.py
djangoldp_i18n/tests/models.py
djangoldp_i18n/tests/runner.py
djangoldp_i18n/tests/tests_cache.py
djangoldp_i18n/tests/tests_get.py
djangoldp_i18n/tests/tests_post.py
djangoldp_i18n/tests/translation.py
djangoldp_i18n-5.0.0.dist-info/METADATA
djangoldp_i18n-5.0.0.dist-info/WHEEL
djangoldp_i18n-5.0.0.dist-info/top_level.txt
djangoldp_i18n-5.0.0.dist-info/RECORD
