Metadata-Version: 2.4
Name: djangoldp_i18n
Version: 5.0.0
Summary: extends Django-Modeltranslation and DjangoLDP's serializer and admin to provide i18n capabilities for DjangoLDP models
Home-page: https://git.startinblox.com/djangoldp-packages/djangoldp-i18n/
Author: Calum Mackervoy
Author-email: calum@startinblox.com
License: copyleft CC NC SA
Classifier: Programming Language :: Python :: 3
Requires-Dist: djangoldp>=5.0.0
Requires-Dist: django-modeltranslation~=0.18.0
